{
  "uuid": "7be0d6de-b124-4322-8fcc-eeb6ed039a62",
  "shortName": "Faster",
  "longName": "Faster Than Walking",
  "companyName": "Spencer Elliott",
  "versionCode": 2,
  "versionLabel": "2.0",
  "watchapp": {
    "watchface": false
  },
  "resources": {
    "media": [
      {
        "menuIcon": true,
        "type": "png",
        "name": "MENU_ICON",
        "file": "images/ic_menu.png"
      },
      {
        "type": "png",
        "name": "LOGO",
        "file": "images/ic_logo_large.png"
      },
      {
        "type": "png",
        "name": "LOCATION_ICON",
        "file": "images/ic_location.png"
      },
      {
        "type": "png",
        "name": "STAR_ICON",
        "file": "images/ic_star.png"
      }
    ]
  }
}
